niced_url_request/__init__.py
niced_url_request/niced_url_request.py
niced_url_request/niced_url_request_test.py
niced_url_request-0.1.dist-info/METADATA
niced_url_request-0.1.dist-info/WHEEL
niced_url_request-0.1.dist-info/top_level.txt
niced_url_request-0.1.dist-info/RECORD
