Metadata-Version: 2.1
Name: niced-url-request
Version: 0.1
Summary: a simple class wrapper to nice URL requests
Home-page: https://github.com/jerabaul29/niced_url_request
Author: Jean Rabault
Author-email: jean.rblt@gmail.com
License: UNKNOWN
Platform: UNKNOWN
Classifier: Programming Language :: Python :: 3
Classifier: License :: OSI Approved :: MIT License
Classifier: Operating System :: OS Independent
Requires-Python: >=3.5
Requires-Dist: raise-assert (>=0.2)
